Topsis/__init__.py
Topsis/topsis_101917169.py
Topsis_Dhaval_101917169-0.0.9.dist-info/LICENSE
Topsis_Dhaval_101917169-0.0.9.dist-info/METADATA
Topsis_Dhaval_101917169-0.0.9.dist-info/WHEEL
Topsis_Dhaval_101917169-0.0.9.dist-info/top_level.txt
Topsis_Dhaval_101917169-0.0.9.dist-info/RECORD
