Metadata-Version: 2.1
Name: Topsis-Dhaval-101917169
Version: 0.0.9
Summary: Topsis program
Home-page: UNKNOWN
Author: Dhaval Arya
Author-email: arya.dhavalv@gmail.com
License: UNKNOWN
Keywords: python,video,stream,video stream,camera stream,sockets
Platform: UNKNOWN
Classifier: Development Status :: 1 - Planning
Classifier: Intended Audience :: Developers
Classifier: Programming Language :: Python :: 3
Classifier: Operating System :: Unix
Classifier: Operating System :: MacOS :: MacOS X
Classifier: Operating System :: Microsoft :: Windows
License-File: LICENSE
Requires-Dist: numpy
Requires-Dist: pandas
